django_lti-0.9.2.dist-info/licenses/LICENSE
lti_tool/__init__.py
lti_tool/admin.py
lti_tool/apps.py
lti_tool/constants.py
lti_tool/decorators.py
lti_tool/factories.py
lti_tool/middleware.py
lti_tool/models.py
lti_tool/types.py
lti_tool/utils.py
lti_tool/views.py
lti_tool/lti_core/__init__.py
lti_tool/lti_core/constants.py
lti_tool/lti_core/utils.py
lti_tool/management/__init__.py
lti_tool/management/commands/__init__.py
lti_tool/management/commands/rotate_keys.py
lti_tool/migrations/0001_initial.py
lti_tool/migrations/0002_create_lti_domain_models.py
lti_tool/migrations/0003_lticontext_memberships_url_ltimembership_is_active.py
lti_tool/migrations/0004_lticontext_can_access_results_and_more.py
lti_tool/migrations/0005_ltilineitem.py
lti_tool/migrations/0006_ltiregistration_audience.py
lti_tool/migrations/0007_lticontext_lti1p1_id_on_platform_and_more.py
lti_tool/migrations/__init__.py
lti_tool/services/__init__.py
lti_tool/services/nrps.py
django_lti-0.9.2.dist-info/METADATA
django_lti-0.9.2.dist-info/WHEEL
django_lti-0.9.2.dist-info/top_level.txt
django_lti-0.9.2.dist-info/RECORD
